{"type":"FeatureCollection","generated_at":"2026-04-23T05:39:39.169Z","region":"miami","bbox":[-80.6,25.55,-80.05,26.05],"category":"airports","feature_count":3,"features":[{"type":"Feature","properties":{"id":"osm-node-541006266","osm_type":"node","osm_id":541006266,"category":"airports","name":"Watson Island International Seaplane Base","operator":null,"ref":null,"tags":{"addr:state":"FL","aerodrome:type":"seaplane","aeroway":"aerodrome","contact:facebook":"https://www.facebook.com/MiamiSeaplaneBase/","contact:instagram":"https://www.instagram.com/miamiseaplanebase/","ele":"0","fixme":"not here","gnis:feature_id":"309661","name":"Watson Island International Seaplane Base","website":"https://www.miamiseaplanebase.com/"}},"geometry":{"type":"Point","coordinates":[-80.1745006,25.7756375]}},{"type":"Feature","properties":{"id":"osm-node-1327354294","osm_type":"node","osm_id":1327354294,"category":"airports","name":"Miami Seaplane Base","operator":null,"ref":"MPB","tags":{"aerodrome":"public","aeroway":"aerodrome","ele":"0","faa":"X44","iata":"MPB","name":"Miami Seaplane Base","owner":"City of Miami","ref":"MPB","type":"public","wikidata":"Q3565275","wikipedia":"en:Miami Seaplane Base"}},"geometry":{"type":"Point","coordinates":[-80.1775503,25.7834634]}},{"type":"Feature","properties":{"id":"osm-node-9678595736","osm_type":"node","osm_id":9678595736,"category":"airports","name":"B & L Farms Airport","operator":null,"ref":null,"tags":{"aeroway":"aerodrome","faa":"11FA","name":"B & L Farms Airport","wikidata":"Q34958923"}},"geometry":{"type":"Point","coordinates":[-80.4989798,25.5824361]}}]}