{"type":"FeatureCollection","generated_at":"2026-04-23T04:04:37.141Z","region":"nyc","bbox":[-74.1,40.55,-73.7,40.92],"category":"sewage","feature_count":1,"features":[{"type":"Feature","properties":{"id":"osm-relation-18231906","osm_type":"relation","osm_id":18231906,"category":"sewage","name":"26th Ward Wastewater Treatment Plant","operator":null,"ref":null,"tags":{"man_made":"wastewater_plant","name":"26th Ward Wastewater Treatment Plant","type":"multipolygon"},"collected_at":"2026-04-23T04:07:15.561Z"},"geometry":{"type":"Point","coordinates":[-73.878863,40.651452]}}]}