{"type":"FeatureCollection","generated_at":"2026-04-23T04:04:37.141Z","region":"nyc","bbox":[-74.1,40.55,-73.7,40.92],"category":"am-fm-antennas","feature_count":2,"features":[{"type":"Feature","properties":{"id":"osm-node-6833159451","osm_type":"node","osm_id":6833159451,"category":"am-fm-antennas","name":null,"operator":null,"ref":null,"tags":{"man_made":"antenna"},"collected_at":"2026-04-23T04:08:22.782Z"},"geometry":{"type":"Point","coordinates":[-74.0407865,40.8112874]}},{"type":"Feature","properties":{"id":"osm-node-6833159454","osm_type":"node","osm_id":6833159454,"category":"am-fm-antennas","name":null,"operator":null,"ref":null,"tags":{"man_made":"antenna"},"collected_at":"2026-04-23T04:08:22.782Z"},"geometry":{"type":"Point","coordinates":[-74.0409199,40.8112972]}}]}