{"type":"FeatureCollection","generated_at":"2026-04-23T05:58:23.707Z","region":"phoenix","bbox":[-112.45,33.25,-111.75,33.8],"category":"am-fm-antennas","feature_count":11,"features":[{"type":"Feature","properties":{"id":"osm-node-5797725852","osm_type":"node","osm_id":5797725852,"category":"am-fm-antennas","name":null,"operator":null,"ref":null,"tags":{"man_made":"antenna"}},"geometry":{"type":"Point","coordinates":[-112.3980179,33.4499129]}},{"type":"Feature","properties":{"id":"osm-node-7647669851","osm_type":"node","osm_id":7647669851,"category":"am-fm-antennas","name":null,"operator":null,"ref":null,"tags":{"man_made":"antenna"}},"geometry":{"type":"Point","coordinates":[-111.9368383,33.3640494]}},{"type":"Feature","properties":{"id":"osm-node-10692346227","osm_type":"node","osm_id":10692346227,"category":"am-fm-antennas","name":null,"operator":null,"ref":null,"tags":{"man_made":"antenna"}},"geometry":{"type":"Point","coordinates":[-112.3543143,33.6825479]}},{"type":"Feature","properties":{"id":"osm-node-11244192613","osm_type":"node","osm_id":11244192613,"category":"am-fm-antennas","name":null,"operator":null,"ref":null,"tags":{"man_made":"antenna"}},"geometry":{"type":"Point","coordinates":[-112.1162191,33.4879938]}},{"type":"Feature","properties":{"id":"osm-node-11993453211","osm_type":"node","osm_id":11993453211,"category":"am-fm-antennas","name":null,"operator":null,"ref":null,"tags":{"communication:radio":"yes","man_made":"antenna"}},"geometry":{"type":"Point","coordinates":[-112.0256074,33.4550859]}},{"type":"Feature","properties":{"id":"osm-node-11993453213","osm_type":"node","osm_id":11993453213,"category":"am-fm-antennas","name":null,"operator":null,"ref":null,"tags":{"communication:radio":"yes","man_made":"antenna"}},"geometry":{"type":"Point","coordinates":[-112.0255171,33.4531894]}},{"type":"Feature","properties":{"id":"osm-node-11993453214","osm_type":"node","osm_id":11993453214,"category":"am-fm-antennas","name":null,"operator":null,"ref":null,"tags":{"communication:radio":"yes","man_made":"antenna"}},"geometry":{"type":"Point","coordinates":[-112.0255036,33.4531894]}},{"type":"Feature","properties":{"id":"osm-node-11993453215","osm_type":"node","osm_id":11993453215,"category":"am-fm-antennas","name":null,"operator":null,"ref":null,"tags":{"communication:radio":"yes","man_made":"antenna"}},"geometry":{"type":"Point","coordinates":[-112.0254753,33.4531893]}},{"type":"Feature","properties":{"id":"osm-node-11993453216","osm_type":"node","osm_id":11993453216,"category":"am-fm-antennas","name":null,"operator":null,"ref":null,"tags":{"communication:radio":"yes","man_made":"antenna"}},"geometry":{"type":"Point","coordinates":[-112.0254637,33.4531893]}},{"type":"Feature","properties":{"id":"osm-node-11993453217","osm_type":"node","osm_id":11993453217,"category":"am-fm-antennas","name":null,"operator":null,"ref":null,"tags":{"communication:radio":"yes","man_made":"antenna"}},"geometry":{"type":"Point","coordinates":[-112.0254525,33.4531892]}},{"type":"Feature","properties":{"id":"osm-node-12773187519","osm_type":"node","osm_id":12773187519,"category":"am-fm-antennas","name":null,"operator":null,"ref":null,"tags":{"communication:mobile_phone":"yes","man_made":"antenna","mimics":"pole","note":"5G Antenna - DAS","tower:construction":"concealed","tower:type":"communication"}},"geometry":{"type":"Point","coordinates":[-111.9259524,33.4932065]}}]}