{"type":"FeatureCollection","generated_at":"2026-04-23T05:58:40.296Z","region":"phoenix","bbox":[-112.45,33.25,-111.75,33.8],"category":"transit-subway","feature_count":2,"features":[{"type":"Feature","properties":{"id":"osm-node-7742141610","osm_type":"node","osm_id":7742141610,"category":"transit-subway","name":"Desert Breeze Rail Station","operator":null,"ref":null,"tags":{"name":"Desert Breeze Rail Station","public_transport":"station","railway":"station","train":"yes"}},"geometry":{"type":"Point","coordinates":[-111.920582,33.314088]}},{"type":"Feature","properties":{"id":"osm-node-7742141611","osm_type":"node","osm_id":7742141611,"category":"transit-subway","name":null,"operator":null,"ref":null,"tags":{"public_transport":"station","railway":"station","train":"yes"}},"geometry":{"type":"Point","coordinates":[-112.412969,33.5501924]}}]}