{"type":"FeatureCollection","generated_at":"2026-04-23T05:24:08.285Z","region":"sf","bbox":[-122.55,37.4,-121.85,38],"category":"sewage","feature_count":3,"features":[{"type":"Feature","properties":{"id":"osm-relation-1866560","osm_type":"relation","osm_id":1866560,"category":"sewage","name":"Silicon Valley Clean Water","operator":null,"ref":null,"tags":{"addr:city":"Redwood City","addr:housenumber":"1400","addr:state":"CA","addr:street":"Radio Road","man_made":"wastewater_plant","name":"Silicon Valley Clean Water","type":"multipolygon","website":"https://svcw.org/"}},"geometry":{"type":"Point","coordinates":[-122.2293137,37.5449949]}},{"type":"Feature","properties":{"id":"osm-relation-13772028","osm_type":"relation","osm_id":13772028,"category":"sewage","name":"San Leandro Water Treatment","operator":null,"ref":null,"tags":{"man_made":"wastewater_plant","name":"San Leandro Water Treatment","source":"Bing","type":"multipolygon"}},"geometry":{"type":"Point","coordinates":[-122.1943568,37.7161811]}},{"type":"Feature","properties":{"id":"osm-relation-13905283","osm_type":"relation","osm_id":13905283,"category":"sewage","name":"South San Francisco Water Quality Control Plant","operator":null,"ref":null,"tags":{"addr:city":"South San Francisco","addr:housenumber":"195","addr:postcode":"94080","addr:street":"Belle Air Road","man_made":"wastewater_plant","name":"South San Francisco Water Quality Control Plant","type":"multipolygon","website":"https://www.ssf.net/departments/public-works/water-quality-control-plant"}},"geometry":{"type":"Point","coordinates":[-122.3965674,37.6416756]}}]}